pyautd3/__init__.py
pyautd3/autd_error.py
pyautd3/py.typed
pyautd3/bin/autd3capi.dll
pyautd3/bin/autd3capi_gain_holo.dll
pyautd3/bin/autd3capi_link_remote.dll
pyautd3/bin/autd3capi_link_twincat.dll
pyautd3/controller/__init__.py
pyautd3/controller/controller.py
pyautd3/controller/environment.py
pyautd3/driver/__init__.py
pyautd3/driver/autd3_device.py
pyautd3/driver/firmware_version.py
pyautd3/driver/link.py
pyautd3/driver/utils.py
pyautd3/driver/common/__init__.py
pyautd3/driver/common/angle.py
pyautd3/driver/common/freq.py
pyautd3/driver/datagram/__init__.py
pyautd3/driver/datagram/clear.py
pyautd3/driver/datagram/datagram.py
pyautd3/driver/datagram/debug.py
pyautd3/driver/datagram/force_fan.py
pyautd3/driver/datagram/gain.py
pyautd3/driver/datagram/group.py
pyautd3/driver/datagram/modulation.py
pyautd3/driver/datagram/output_mask.py
pyautd3/driver/datagram/phase_corr.py
pyautd3/driver/datagram/pulse_width_encoder.py
pyautd3/driver/datagram/reads_fpga_state.py
pyautd3/driver/datagram/segment.py
pyautd3/driver/datagram/synchronize.py
pyautd3/driver/datagram/with_finite_loop.py
pyautd3/driver/datagram/with_segment.py
pyautd3/driver/datagram/silencer/__init__.py
pyautd3/driver/datagram/silencer/fixed_completion_steps.py
pyautd3/driver/datagram/silencer/fixed_completion_time.py
pyautd3/driver/datagram/silencer/fixed_update_rate.py
pyautd3/driver/datagram/silencer/silencer.py
pyautd3/driver/datagram/stm/__init__.py
pyautd3/driver/datagram/stm/control_point.py
pyautd3/driver/datagram/stm/foci.py
pyautd3/driver/datagram/stm/gain.py
pyautd3/driver/datagram/stm/stm_sampling_config.py
pyautd3/driver/firmware/fpga/__init__.py
pyautd3/driver/firmware/fpga/drive.py
pyautd3/driver/firmware/fpga/emit_intensity.py
pyautd3/driver/firmware/fpga/fpga_state.py
pyautd3/driver/firmware/fpga/phase.py
pyautd3/driver/firmware/fpga/pulse_width.py
pyautd3/driver/firmware/fpga/sampling_config.py
pyautd3/driver/firmware/fpga/transition_mode.py
pyautd3/driver/geometry/__init__.py
pyautd3-38.0.0.dist-info/licenses/LICENSE
pyautd3-38.0.0.dist-info/METADATA
pyautd3-38.0.0.dist-info/WHEEL
pyautd3-38.0.0.dist-info/top_level.txt
pyautd3-38.0.0.dist-info/RECORD
